{
  "version": "5",
  "dialect": "mysql",
  "id": "688e6abc-2179-42b9-8dfc-32d8678f0781",
  "prevId": "a114169f-bf8a-4493-b6a6-9bfc9090f8fa",
  "tables": {
    "clienteFichas": {
      "name": "clienteFichas",
      "columns": {
        "id": {
          "name": "id",
          "type": "int",
          "primaryKey": false,
          "notNull": true,
          "autoincrement": true
        },
        "clienteId": {
          "name": "clienteId",
          "type": "int",
          "primaryKey": false,
          "notNull": true,
          "autoincrement": false
        },
        "arquivoPath": {
          "name": "arquivoPath",
          "type": "varchar(500)",
          "primaryKey": false,
          "notNull": true,
          "autoincrement": false
        },
        "arquivoUrl": {
          "name": "arquivoUrl",
          "type": "varchar(500)",
          "primaryKey": false,
          "notNull": true,
          "autoincrement": false
        },
        "criadoEm": {
          "name": "criadoEm",
          "type": "timestamp",
          "primaryKey": false,
          "notNull": true,
          "autoincrement": false,
          "default": "(now())"
        }
      },
      "indexes": {},
      "foreignKeys": {
        "clienteFichas_clienteId_clientes_id_fk": {
          "name": "clienteFichas_clienteId_clientes_id_fk",
          "tableFrom": "clienteFichas",
          "tableTo": "clientes",
          "columnsFrom": [
            "clienteId"
          ],
          "columnsTo": [
            "id"
          ],
          "onDelete": "no action",
          "onUpdate": "no action"
        }
      },
      "compositePrimaryKeys": {
        "clienteFichas_id": {
          "name": "clienteFichas_id",
          "columns": [
            "id"
          ]
        }
      },
      "uniqueConstraints": {},
      "checkConstraint": {}
    },
    "clientes": {
      "name": "clientes",
      "columns": {
        "id": {
          "name": "id",
          "type": "int",
          "primaryKey": false,
          "notNull": true,
          "autoincrement": true
        },
        "tipo": {
          "name": "tipo",
          "type": "enum('PF','PJ')",
          "primaryKey": false,
          "notNull": true,
          "autoincrement": false,
          "default": "'PF'"
        },
        "nomeRazao": {
          "name": "nomeRazao",
          "type": "varchar(180)",
          "primaryKey": false,
          "notNull": true,
          "autoincrement": false
        },
        "cpfCnpj": {
          "name": "cpfCnpj",
          "type": "varchar(25)",
          "primaryKey": false,
          "notNull": true,
          "autoincrement": false
        },
        "rgIe": {
          "name": "rgIe",
          "type": "varchar(25)",
          "primaryKey": false,
          "notNull": false,
          "autoincrement": false
        },
        "nascimento": {
          "name": "nascimento",
          "type": "date",
          "primaryKey": false,
          "notNull": false,
          "autoincrement": false
        },
        "telefone1": {
          "name": "telefone1",
          "type": "varchar(30)",
          "primaryKey": false,
          "notNull": false,
          "autoincrement": false
        },
        "telefone2": {
          "name": "telefone2",
          "type": "varchar(30)",
          "primaryKey": false,
          "notNull": false,
          "autoincrement": false
        },
        "whatsapp": {
          "name": "whatsapp",
          "type": "varchar(30)",
          "primaryKey": false,
          "notNull": false,
          "autoincrement": false
        },
        "email": {
          "name": "email",
          "type": "varchar(180)",
          "primaryKey": false,
          "notNull": false,
          "autoincrement": false
        },
        "cep": {
          "name": "cep",
          "type": "varchar(12)",
          "primaryKey": false,
          "notNull": false,
          "autoincrement": false
        },
        "rua": {
          "name": "rua",
          "type": "varchar(180)",
          "primaryKey": false,
          "notNull": false,
          "autoincrement": false
        },
        "numero": {
          "name": "numero",
          "type": "varchar(20)",
          "primaryKey": false,
          "notNull": false,
          "autoincrement": false
        },
        "bairro": {
          "name": "bairro",
          "type": "varchar(120)",
          "primaryKey": false,
          "notNull": false,
          "autoincrement": false
        },
        "cidade": {
          "name": "cidade",
          "type": "varchar(120)",
          "primaryKey": false,
          "notNull": false,
          "autoincrement": false
        },
        "uf": {
          "name": "uf",
          "type": "varchar(2)",
          "primaryKey": false,
          "notNull": false,
          "autoincrement": false
        },
        "complemento": {
          "name": "complemento",
          "type": "varchar(120)",
          "primaryKey": false,
          "notNull": false,
          "autoincrement": false
        },
        "referencia": {
          "name": "referencia",
          "type": "varchar(180)",
          "primaryKey": false,
          "notNull": false,
          "autoincrement": false
        },
        "observacoes": {
          "name": "observacoes",
          "type": "text",
          "primaryKey": false,
          "notNull": false,
          "autoincrement": false
        },
        "criadoEm": {
          "name": "criadoEm",
          "type": "timestamp",
          "primaryKey": false,
          "notNull": true,
          "autoincrement": false,
          "default": "(now())"
        },
        "atualizadoEm": {
          "name": "atualizadoEm",
          "type": "timestamp",
          "primaryKey": false,
          "notNull": true,
          "autoincrement": false,
          "onUpdate": true,
          "default": "(now())"
        }
      },
      "indexes": {},
      "foreignKeys": {},
      "compositePrimaryKeys": {
        "clientes_id": {
          "name": "clientes_id",
          "columns": [
            "id"
          ]
        }
      },
      "uniqueConstraints": {},
      "checkConstraint": {}
    },
    "funcionarios": {
      "name": "funcionarios",
      "columns": {
        "id": {
          "name": "id",
          "type": "int",
          "primaryKey": false,
          "notNull": true,
          "autoincrement": true
        },
        "nome": {
          "name": "nome",
          "type": "varchar(120)",
          "primaryKey": false,
          "notNull": true,
          "autoincrement": false
        },
        "email": {
          "name": "email",
          "type": "varchar(180)",
          "primaryKey": false,
          "notNull": true,
          "autoincrement": false
        },
        "senhaHash": {
          "name": "senhaHash",
          "type": "varchar(255)",
          "primaryKey": false,
          "notNull": true,
          "autoincrement": false
        },
        "perfil": {
          "name": "perfil",
          "type": "enum('ADMIN','FUNCIONARIO')",
          "primaryKey": false,
          "notNull": true,
          "autoincrement": false,
          "default": "'FUNCIONARIO'"
        },
        "telefone": {
          "name": "telefone",
          "type": "varchar(30)",
          "primaryKey": false,
          "notNull": false,
          "autoincrement": false
        },
        "cargo": {
          "name": "cargo",
          "type": "varchar(80)",
          "primaryKey": false,
          "notNull": false,
          "autoincrement": false
        },
        "ativo": {
          "name": "ativo",
          "type": "int",
          "primaryKey": false,
          "notNull": true,
          "autoincrement": false,
          "default": 1
        },
        "criadoEm": {
          "name": "criadoEm",
          "type": "timestamp",
          "primaryKey": false,
          "notNull": true,
          "autoincrement": false,
          "default": "(now())"
        },
        "atualizadoEm": {
          "name": "atualizadoEm",
          "type": "timestamp",
          "primaryKey": false,
          "notNull": true,
          "autoincrement": false,
          "onUpdate": true,
          "default": "(now())"
        }
      },
      "indexes": {},
      "foreignKeys": {},
      "compositePrimaryKeys": {
        "funcionarios_id": {
          "name": "funcionarios_id",
          "columns": [
            "id"
          ]
        }
      },
      "uniqueConstraints": {
        "funcionarios_email_unique": {
          "name": "funcionarios_email_unique",
          "columns": [
            "email"
          ]
        }
      },
      "checkConstraint": {}
    },
    "instalacaoFotos": {
      "name": "instalacaoFotos",
      "columns": {
        "id": {
          "name": "id",
          "type": "int",
          "primaryKey": false,
          "notNull": true,
          "autoincrement": true
        },
        "instalacaoId": {
          "name": "instalacaoId",
          "type": "int",
          "primaryKey": false,
          "notNull": true,
          "autoincrement": false
        },
        "arquivoPath": {
          "name": "arquivoPath",
          "type": "varchar(500)",
          "primaryKey": false,
          "notNull": true,
          "autoincrement": false
        },
        "arquivoUrl": {
          "name": "arquivoUrl",
          "type": "varchar(500)",
          "primaryKey": false,
          "notNull": true,
          "autoincrement": false
        },
        "criadoEm": {
          "name": "criadoEm",
          "type": "timestamp",
          "primaryKey": false,
          "notNull": true,
          "autoincrement": false,
          "default": "(now())"
        }
      },
      "indexes": {},
      "foreignKeys": {
        "instalacaoFotos_instalacaoId_instalacoes_id_fk": {
          "name": "instalacaoFotos_instalacaoId_instalacoes_id_fk",
          "tableFrom": "instalacaoFotos",
          "tableTo": "instalacoes",
          "columnsFrom": [
            "instalacaoId"
          ],
          "columnsTo": [
            "id"
          ],
          "onDelete": "no action",
          "onUpdate": "no action"
        }
      },
      "compositePrimaryKeys": {
        "instalacaoFotos_id": {
          "name": "instalacaoFotos_id",
          "columns": [
            "id"
          ]
        }
      },
      "uniqueConstraints": {},
      "checkConstraint": {}
    },
    "instalacaoMateriais": {
      "name": "instalacaoMateriais",
      "columns": {
        "id": {
          "name": "id",
          "type": "int",
          "primaryKey": false,
          "notNull": true,
          "autoincrement": true
        },
        "instalacaoId": {
          "name": "instalacaoId",
          "type": "int",
          "primaryKey": false,
          "notNull": true,
          "autoincrement": false
        },
        "produtoId": {
          "name": "produtoId",
          "type": "int",
          "primaryKey": false,
          "notNull": true,
          "autoincrement": false
        },
        "quantidade": {
          "name": "quantidade",
          "type": "decimal(12,2)",
          "primaryKey": false,
          "notNull": true,
          "autoincrement": false
        },
        "observacoes": {
          "name": "observacoes",
          "type": "varchar(255)",
          "primaryKey": false,
          "notNull": false,
          "autoincrement": false
        },
        "criadoEm": {
          "name": "criadoEm",
          "type": "timestamp",
          "primaryKey": false,
          "notNull": true,
          "autoincrement": false,
          "default": "(now())"
        }
      },
      "indexes": {},
      "foreignKeys": {
        "instalacaoMateriais_instalacaoId_instalacoes_id_fk": {
          "name": "instalacaoMateriais_instalacaoId_instalacoes_id_fk",
          "tableFrom": "instalacaoMateriais",
          "tableTo": "instalacoes",
          "columnsFrom": [
            "instalacaoId"
          ],
          "columnsTo": [
            "id"
          ],
          "onDelete": "no action",
          "onUpdate": "no action"
        },
        "instalacaoMateriais_produtoId_produtos_id_fk": {
          "name": "instalacaoMateriais_produtoId_produtos_id_fk",
          "tableFrom": "instalacaoMateriais",
          "tableTo": "produtos",
          "columnsFrom": [
            "produtoId"
          ],
          "columnsTo": [
            "id"
          ],
          "onDelete": "no action",
          "onUpdate": "no action"
        }
      },
      "compositePrimaryKeys": {
        "instalacaoMateriais_id": {
          "name": "instalacaoMateriais_id",
          "columns": [
            "id"
          ]
        }
      },
      "uniqueConstraints": {},
      "checkConstraint": {}
    },
    "instalacoes": {
      "name": "instalacoes",
      "columns": {
        "id": {
          "name": "id",
          "type": "int",
          "primaryKey": false,
          "notNull": true,
          "autoincrement": true
        },
        "clienteId": {
          "name": "clienteId",
          "type": "int",
          "primaryKey": false,
          "notNull": true,
          "autoincrement": false
        },
        "tipo": {
          "name": "tipo",
          "type": "enum('ALARME','CAMERA','CERCA')",
          "primaryKey": false,
          "notNull": true,
          "autoincrement": false
        },
        "enderecoExecucao": {
          "name": "enderecoExecucao",
          "type": "varchar(255)",
          "primaryKey": false,
          "notNull": false,
          "autoincrement": false
        },
        "dataPrevista": {
          "name": "dataPrevista",
          "type": "date",
          "primaryKey": false,
          "notNull": false,
          "autoincrement": false
        },
        "funcionarioId": {
          "name": "funcionarioId",
          "type": "int",
          "primaryKey": false,
          "notNull": false,
          "autoincrement": false
        },
        "status": {
          "name": "status",
          "type": "enum('PENDENTE','EM_ANDAMENTO','CONCLUIDA','CANCELADA')",
          "primaryKey": false,
          "notNull": true,
          "autoincrement": false,
          "default": "'PENDENTE'"
        },
        "observacoes": {
          "name": "observacoes",
          "type": "text",
          "primaryKey": false,
          "notNull": false,
          "autoincrement": false
        },
        "criadoEm": {
          "name": "criadoEm",
          "type": "timestamp",
          "primaryKey": false,
          "notNull": true,
          "autoincrement": false,
          "default": "(now())"
        },
        "atualizadoEm": {
          "name": "atualizadoEm",
          "type": "timestamp",
          "primaryKey": false,
          "notNull": true,
          "autoincrement": false,
          "onUpdate": true,
          "default": "(now())"
        },
        "finalizadoEm": {
          "name": "finalizadoEm",
          "type": "datetime",
          "primaryKey": false,
          "notNull": false,
          "autoincrement": false
        }
      },
      "indexes": {},
      "foreignKeys": {
        "instalacoes_clienteId_clientes_id_fk": {
          "name": "instalacoes_clienteId_clientes_id_fk",
          "tableFrom": "instalacoes",
          "tableTo": "clientes",
          "columnsFrom": [
            "clienteId"
          ],
          "columnsTo": [
            "id"
          ],
          "onDelete": "no action",
          "onUpdate": "no action"
        },
        "instalacoes_funcionarioId_funcionarios_id_fk": {
          "name": "instalacoes_funcionarioId_funcionarios_id_fk",
          "tableFrom": "instalacoes",
          "tableTo": "funcionarios",
          "columnsFrom": [
            "funcionarioId"
          ],
          "columnsTo": [
            "id"
          ],
          "onDelete": "no action",
          "onUpdate": "no action"
        }
      },
      "compositePrimaryKeys": {
        "instalacoes_id": {
          "name": "instalacoes_id",
          "columns": [
            "id"
          ]
        }
      },
      "uniqueConstraints": {},
      "checkConstraint": {}
    },
    "logsAuditoria": {
      "name": "logsAuditoria",
      "columns": {
        "id": {
          "name": "id",
          "type": "int",
          "primaryKey": false,
          "notNull": true,
          "autoincrement": true
        },
        "funcionarioId": {
          "name": "funcionarioId",
          "type": "int",
          "primaryKey": false,
          "notNull": false,
          "autoincrement": false
        },
        "acao": {
          "name": "acao",
          "type": "varchar(120)",
          "primaryKey": false,
          "notNull": true,
          "autoincrement": false
        },
        "entidade": {
          "name": "entidade",
          "type": "varchar(80)",
          "primaryKey": false,
          "notNull": true,
          "autoincrement": false
        },
        "entidadeId": {
          "name": "entidadeId",
          "type": "int",
          "primaryKey": false,
          "notNull": false,
          "autoincrement": false
        },
        "detalhes": {
          "name": "detalhes",
          "type": "json",
          "primaryKey": false,
          "notNull": false,
          "autoincrement": false
        },
        "criadoEm": {
          "name": "criadoEm",
          "type": "timestamp",
          "primaryKey": false,
          "notNull": true,
          "autoincrement": false,
          "default": "(now())"
        }
      },
      "indexes": {},
      "foreignKeys": {
        "logsAuditoria_funcionarioId_funcionarios_id_fk": {
          "name": "logsAuditoria_funcionarioId_funcionarios_id_fk",
          "tableFrom": "logsAuditoria",
          "tableTo": "funcionarios",
          "columnsFrom": [
            "funcionarioId"
          ],
          "columnsTo": [
            "id"
          ],
          "onDelete": "no action",
          "onUpdate": "no action"
        }
      },
      "compositePrimaryKeys": {
        "logsAuditoria_id": {
          "name": "logsAuditoria_id",
          "columns": [
            "id"
          ]
        }
      },
      "uniqueConstraints": {},
      "checkConstraint": {}
    },
    "pontos": {
      "name": "pontos",
      "columns": {
        "id": {
          "name": "id",
          "type": "int",
          "primaryKey": false,
          "notNull": true,
          "autoincrement": true
        },
        "funcionarioId": {
          "name": "funcionarioId",
          "type": "int",
          "primaryKey": false,
          "notNull": true,
          "autoincrement": false
        },
        "data": {
          "name": "data",
          "type": "date",
          "primaryKey": false,
          "notNull": true,
          "autoincrement": false
        },
        "horaEntrada": {
          "name": "horaEntrada",
          "type": "datetime",
          "primaryKey": false,
          "notNull": false,
          "autoincrement": false
        },
        "horaInicioAlmoco": {
          "name": "horaInicioAlmoco",
          "type": "datetime",
          "primaryKey": false,
          "notNull": false,
          "autoincrement": false
        },
        "horaFimAlmoco": {
          "name": "horaFimAlmoco",
          "type": "datetime",
          "primaryKey": false,
          "notNull": false,
          "autoincrement": false
        },
        "horaSaida": {
          "name": "horaSaida",
          "type": "datetime",
          "primaryKey": false,
          "notNull": false,
          "autoincrement": false
        },
        "criadoEm": {
          "name": "criadoEm",
          "type": "timestamp",
          "primaryKey": false,
          "notNull": true,
          "autoincrement": false,
          "default": "(now())"
        },
        "atualizadoEm": {
          "name": "atualizadoEm",
          "type": "timestamp",
          "primaryKey": false,
          "notNull": true,
          "autoincrement": false,
          "onUpdate": true,
          "default": "(now())"
        }
      },
      "indexes": {},
      "foreignKeys": {
        "pontos_funcionarioId_funcionarios_id_fk": {
          "name": "pontos_funcionarioId_funcionarios_id_fk",
          "tableFrom": "pontos",
          "tableTo": "funcionarios",
          "columnsFrom": [
            "funcionarioId"
          ],
          "columnsTo": [
            "id"
          ],
          "onDelete": "no action",
          "onUpdate": "no action"
        }
      },
      "compositePrimaryKeys": {
        "pontos_id": {
          "name": "pontos_id",
          "columns": [
            "id"
          ]
        }
      },
      "uniqueConstraints": {
        "uniq_ponto_func_data": {
          "name": "uniq_ponto_func_data",
          "columns": [
            "funcionarioId",
            "data"
          ]
        }
      },
      "checkConstraint": {}
    },
    "produtos": {
      "name": "produtos",
      "columns": {
        "id": {
          "name": "id",
          "type": "int",
          "primaryKey": false,
          "notNull": true,
          "autoincrement": true
        },
        "codigo": {
          "name": "codigo",
          "type": "varchar(30)",
          "primaryKey": false,
          "notNull": false,
          "autoincrement": false
        },
        "nome": {
          "name": "nome",
          "type": "varchar(220)",
          "primaryKey": false,
          "notNull": true,
          "autoincrement": false
        },
        "categoria": {
          "name": "categoria",
          "type": "enum('ALARME','CAMERA','CERCA','OUTROS')",
          "primaryKey": false,
          "notNull": true,
          "autoincrement": false
        },
        "unidade": {
          "name": "unidade",
          "type": "varchar(20)",
          "primaryKey": false,
          "notNull": false,
          "autoincrement": false,
          "default": "'un'"
        },
        "estoque": {
          "name": "estoque",
          "type": "decimal(12,2)",
          "primaryKey": false,
          "notNull": false,
          "autoincrement": false,
          "default": "'0'"
        },
        "ativo": {
          "name": "ativo",
          "type": "int",
          "primaryKey": false,
          "notNull": true,
          "autoincrement": false,
          "default": 1
        },
        "criadoEm": {
          "name": "criadoEm",
          "type": "timestamp",
          "primaryKey": false,
          "notNull": true,
          "autoincrement": false,
          "default": "(now())"
        },
        "atualizadoEm": {
          "name": "atualizadoEm",
          "type": "timestamp",
          "primaryKey": false,
          "notNull": true,
          "autoincrement": false,
          "onUpdate": true,
          "default": "(now())"
        }
      },
      "indexes": {},
      "foreignKeys": {},
      "compositePrimaryKeys": {
        "produtos_id": {
          "name": "produtos_id",
          "columns": [
            "id"
          ]
        }
      },
      "uniqueConstraints": {},
      "checkConstraint": {}
    },
    "users": {
      "name": "users",
      "columns": {
        "id": {
          "name": "id",
          "type": "int",
          "primaryKey": false,
          "notNull": true,
          "autoincrement": true
        },
        "openId": {
          "name": "openId",
          "type": "varchar(64)",
          "primaryKey": false,
          "notNull": true,
          "autoincrement": false
        },
        "name": {
          "name": "name",
          "type": "text",
          "primaryKey": false,
          "notNull": false,
          "autoincrement": false
        },
        "email": {
          "name": "email",
          "type": "varchar(320)",
          "primaryKey": false,
          "notNull": false,
          "autoincrement": false
        },
        "loginMethod": {
          "name": "loginMethod",
          "type": "varchar(64)",
          "primaryKey": false,
          "notNull": false,
          "autoincrement": false
        },
        "role": {
          "name": "role",
          "type": "enum('user','admin')",
          "primaryKey": false,
          "notNull": true,
          "autoincrement": false,
          "default": "'user'"
        },
        "createdAt": {
          "name": "createdAt",
          "type": "timestamp",
          "primaryKey": false,
          "notNull": true,
          "autoincrement": false,
          "default": "(now())"
        },
        "updatedAt": {
          "name": "updatedAt",
          "type": "timestamp",
          "primaryKey": false,
          "notNull": true,
          "autoincrement": false,
          "onUpdate": true,
          "default": "(now())"
        },
        "lastSignedIn": {
          "name": "lastSignedIn",
          "type": "timestamp",
          "primaryKey": false,
          "notNull": true,
          "autoincrement": false,
          "default": "(now())"
        }
      },
      "indexes": {},
      "foreignKeys": {},
      "compositePrimaryKeys": {
        "users_id": {
          "name": "users_id",
          "columns": [
            "id"
          ]
        }
      },
      "uniqueConstraints": {
        "users_openId_unique": {
          "name": "users_openId_unique",
          "columns": [
            "openId"
          ]
        }
      },
      "checkConstraint": {}
    }
  },
  "views": {},
  "_meta": {
    "schemas": {},
    "tables": {},
    "columns": {}
  },
  "internal": {
    "tables": {},
    "indexes": {}
  }
}